<annotation>
	<folder>face08</folder>
	<filename>0573.jpg</filename>
	<path>/home/benamara/Desktop/Python Projects/db/Terravic Facial Infrared Database/face08/0573.jpg</path>
	<source>
		<database>Unknown</database>
	</source>
	<size>
		<width>320</width>
		<height>240</height>
		<depth>1</depth>
	</size>
	<segmented>0</segmented>
	<object>
		<name>thermal_face</name>
		<pose>Unspecified</pose>
		<truncated>0</truncated>
		<difficult>0</difficult>
		<bndbox>
			<xmin>103</xmin>
			<ymin>56</ymin>
			<xmax>226</xmax>
			<ymax>197</ymax>
		</bndbox>
	</object>
</annotation>
